examples/__init__.py
examples/airline/__init__.py
examples/airline/main.py
examples/airline/configs/__init__.py
examples/airline/configs/bees.py
examples/airline/configs/tools.py
examples/shopper_bee/__init__.py
examples/shopper_bee/database.py
examples/shopper_bee/main.py
examples/support_bee/__init__.py
examples/support_bee/customer_service.py
examples/support_bee/main.py
examples/support_bee/prep_data.py
swarm/__init__.py
swarm/core.py
swarm/types.py
swarm/util.py
swarm/repl/__init__.py
swarm/repl/repl.py
tests/__init__.py
tests/mock_client.py
tests/test_core.py
tests/test_util.py
aibeehive-0.1.0.dist-info/LICENSE
aibeehive-0.1.0.dist-info/METADATA
aibeehive-0.1.0.dist-info/WHEEL
aibeehive-0.1.0.dist-info/top_level.txt
aibeehive-0.1.0.dist-info/zip-safe
aibeehive-0.1.0.dist-info/RECORD
